edgegap_consul/__init__.py
edgegap_consul/_client.py
edgegap_consul/_configuration.py
edgegap_consul/_factory.py
edgegap_consul/_reader.py
edgegap_consul-1.11.12.dist-info/LICENSE
edgegap_consul-1.11.12.dist-info/METADATA
edgegap_consul-1.11.12.dist-info/WHEEL
edgegap_consul-1.11.12.dist-info/RECORD
